azt.py
azt-0.0.7.dist-info/LICENSE
azt-0.0.7.dist-info/METADATA
azt-0.0.7.dist-info/WHEEL
azt-0.0.7.dist-info/entry_points.txt
azt-0.0.7.dist-info/top_level.txt
azt-0.0.7.dist-info/RECORD
