Metadata-Version: 2.1
Name: azt
Version: 0.0.7
Summary: ~azt is an intelligent hybrid progressive programming language
Home-page: https://build.azat.ai/azt/
Author: Yaakov Azat
Author-email: yaakovazat@gmail.com
License: UNKNOWN
Keywords: azt AzatAI development
Platform: UNKNOWN
Classifier: Development Status :: 3 - Alpha
Classifier: Intended Audience :: Developers
Classifier: Topic :: Software Development :: Build Tools
Classifier: Programming Language :: Python :: 3
Classifier: Programming Language :: Python :: 3.5
Classifier: Programming Language :: Python :: 3.6
Classifier: Programming Language :: Python :: 3.7
Requires-Python: >=3.*
Requires-Dist: click
Requires-Dist: pyfiglet
